hack4u/__init__.py
hack4u/courses.py
hack4u/utils.py
hack_for_u_courses_radoslav-0.6.0.dist-info/METADATA
hack_for_u_courses_radoslav-0.6.0.dist-info/WHEEL
hack_for_u_courses_radoslav-0.6.0.dist-info/top_level.txt
hack_for_u_courses_radoslav-0.6.0.dist-info/RECORD
