Metadata-Version: 2.4
Name: Hack_for_u_Courses_RADOSLAV
Version: 0.6.0
Summary: Una biblioteca para consultar cursos de hack4u.
Home-page: https://hack4u.io
Author: Radoslav Radkov
Dynamic: author
Dynamic: description-content-type
Dynamic: home-page
Dynamic: summary
